apkcat/__init__.py
apkcat/cli/__init__.py
apkcat/cli/cli.py
apkcat/config/__init__.py
apkcat/core/__init__.py
apkcat/core/apkinfo.py
apkcat/core/main.py
apkcat/integration/__init__.py
apkcat/integration/bazaar.py
apkcat/integration/osint_main.py
apkcat/integration/triage.py
apkcat-0.0.7.dist-info/LICENSE
apkcat-0.0.7.dist-info/METADATA
apkcat-0.0.7.dist-info/WHEEL
apkcat-0.0.7.dist-info/entry_points.txt
apkcat-0.0.7.dist-info/top_level.txt
apkcat-0.0.7.dist-info/RECORD
